xrectsel/__init__.py
xrectsel/console.py
python_xrectsel-1.5.dist-info/LICENSE
python_xrectsel-1.5.dist-info/METADATA
python_xrectsel-1.5.dist-info/WHEEL
python_xrectsel-1.5.dist-info/entry_points.txt
python_xrectsel-1.5.dist-info/top_level.txt
python_xrectsel-1.5.dist-info/RECORD
