Metadata-Version: 2.1
Name: python-xrectsel
Version: 1.5
Summary: Geometry of a rectangular screen region
Home-page: https://github.com/digitronik/python-xrectsel
Author: Nikhil Dhandre
Author-email: nik.digitronik@live.com
License: GPLv3
Keywords: xrectsel,python-xrectsel
Classifier: Natural Language :: English
Classifier: Operating System :: OS Independent
Classifier: Development Status :: 2 - Pre-Alpha
Classifier: Intended Audience :: Developers
Classifier: Topic :: Utilities
Classifier: Topic :: Software Development :: User Interfaces
Classifier: Programming Language :: Python :: 3.7
Classifier: Programming Language :: Python :: 3.8
Classifier: Programming Language :: Python :: 3.9
Classifier: Programming Language :: Python :: 3.10
Requires-Python: >=3.4
License-File: LICENSE
Requires-Dist: python-xlib
Requires-Dist: click
